raw_telegram/__init__.py
raw_telegram/api.py
raw_telegram_api-1.2.dist-info/LICENSE
raw_telegram_api-1.2.dist-info/METADATA
raw_telegram_api-1.2.dist-info/WHEEL
raw_telegram_api-1.2.dist-info/top_level.txt
raw_telegram_api-1.2.dist-info/RECORD
