Metadata-Version: 2.1
Name: raw-telegram-api
Version: 1.2
Summary: Raw Telegram API
Author: mishpro
Author-email: mishpro <root@venusbiser.ru>
Project-URL: Homepage, https://github.com/mishpro-programm/raw-telegram-api
Project-URL: Bug Tracker, https://github.com/mishpro-programm/raw-telegram-api/issues
Classifier: Programming Language :: Python :: 3
Classifier: License :: OSI Approved :: MIT License
Classifier: Operating System :: OS Independent
Requires-Python: >3
License-File: LICENSE
Requires-Dist: requests (>=2.30.0)
